ampari/__init__.py
ampari/main.py
ampari-0.1.6.dist-info/LICENSE
ampari-0.1.6.dist-info/METADATA
ampari-0.1.6.dist-info/WHEEL
ampari-0.1.6.dist-info/top_level.txt
ampari-0.1.6.dist-info/RECORD
