Metadata-Version: 2.1
Name: ampari
Version: 0.1.6
License: MIT
License-File: LICENSE
Requires-Dist: requests
Provides-Extra: dev
Requires-Dist: twine >=5.1.0 ; extra == 'dev'
